lrl/__init__.py
lrl/version.py
lrl/data_stores/__init__.py
lrl/data_stores/data_stores.py
lrl/environments/__init__.py
lrl/environments/frozen_lake.py
lrl/environments/racetrack.py
lrl/environments/utils.py
lrl/solvers/__init__.py
lrl/solvers/base_solver.py
lrl/solvers/learners.py
lrl/solvers/planners.py
lrl/utils/__init__.py
lrl/utils/experiment_runners.py
lrl/utils/misc.py
lrl/utils/plotting.py
lrl/utils/sphinx_ext.py
lrl-1.0.0.dist-info/LICENSE
lrl-1.0.0.dist-info/METADATA
lrl-1.0.0.dist-info/WHEEL
lrl-1.0.0.dist-info/top_level.txt
lrl-1.0.0.dist-info/RECORD
