Metadata-Version: 2.1
Name: lrl
Version: 1.0.0
Summary: lrl: Learn Reinforcement Learning
Home-page: https://github.com/ca-scribner/lrl
Author: Andrew Scribner
License: BSD 3
Platform: UNKNOWN
Requires-Python: >3.6
Requires-Dist: gym (>=0.12.1)
Requires-Dist: matplotlib (>=3.0.3)
Requires-Dist: ipython (>=7.5.0)
Requires-Dist: pandas (>=0.24.2)
Requires-Dist: scikit-learn (>=0.20.3)
